HELP.md
LICENSE.md
LICENSE.md.pre
README.md
README.md.em
em.py
emdoc.py
emhelp.py
emlib.py
setup.py
test.sh
empy.egg-info/PKG-INFO
empy.egg-info/SOURCES.txt
empy.egg-info/dependency_links.txt
empy.egg-info/top_level.txt